{
  "created_at": "2025-05-01T15:34:31.095480+00:00",
  "elapsed": 0.176113,
  "encoding": "utf-8",
  "headers": {
    "Cache-Control": "private, no-store",
    "Connection": "keep-alive",
    "Content-Length": "3745",
    "Content-Type": "application/json",
    "Date": "Thu, 01 May 2025 15:34:31 GMT",
    "Strict-Transport-Security": "max-age=31536000",
    "Vary": "Origin",
    "X-Content-Type-Options": "nosniff",
    "X-Frame-Options": "DENY",
    "X-XSS-Protection": "1;mode=block"
  },
  "reason": "",
  "request": {
    "body": "",
    "cookies": {
      "TS0193e6a1": "01283c52a4685389b04d24928d59124b3a512fb85755dc771bca47a6b2a92df4d0a97e08410c6afeacdef43c9a1b82f5a09618a199"
    },
    "headers": {
      "Accept": "*/*",
      "Accept-Encoding": "gzip, deflate, br",
      "Connection": "keep-alive",
      "Cookie": "TS0193e6a1=01283c52a4685389b04d24928d59124b3a512fb85755dc771bca47a6b2a92df4d0a97e08410c6afeacdef43c9a1b82f5a09618a199",
      "User-Agent": "python-requests/2.32.3"
    },
    "method": "GET",
    "url": "https://geocoding.geo.census.gov/geocoder/geographies/coordinates?benchmark=Public_AR_Census2020&format=json&vintage=Census2020_Census2020&x=-106.717536&y=42.548412"
  },
  "status_code": 200,
  "url": "https://geocoding.geo.census.gov/geocoder/geographies/coordinates?benchmark=Public_AR_Census2020&format=json&vintage=Census2020_Census2020&x=-106.717536&y=42.548412",
  "_decoded_content": {
    "result": {
      "geographies": {
        "State Legislative Districts - Upper": [
          {
            "POP100": 19412,
            "GEOID": "56030",
            "CENTLAT": "+42.9673323",
            "AREAWATER": 87893742,
            "STATE": "56",
            "BASENAME": "30",
            "OID": "212904690192244",
            "LSADC": "LU",
            "SLDU": "030",
            "FUNCSTAT": "N",
            "INTPTLAT": "+42.9635314",
            "NAME": "State Senate District 30",
            "OBJECTID": 831,
            "CENTLON": "-106.8237159",
            "LSY": "2018",
            "HU100": 8345,
            "AREALAND": 13220201710,
            "INTPTLON": "-106.8264876",
            "MTFCC": "G5210",
            "LDTYP": "O"
          }
        ],
        "States": [
          {
            "STATENS": "01779807",
            "POP100": 576851,
            "GEOID": "56",
            "CENTLAT": "+42.9960999",
            "AREAWATER": 1867503715,
            "STATE": "56",
            "BASENAME": "Wyoming",
            "STUSAB": "WY",
            "OID": "27490227778497",
            "LSADC": "00",
            "FUNCSTAT": "A",
            "INTPTLAT": "+42.9896591",
            "DIVISION": "8",
            "NAME": "Wyoming",
            "REGION": "4",
            "OBJECTID": 46,
            "CENTLON": "-107.5514568",
            "AREALAND": 251458712277,
            "INTPTLON": "-107.5443922",
            "HU100": 271887,
            "MTFCC": "G4000",
            "UR": "M"
          }
        ],
        "County Subdivisions": [
          {
            "COUSUB": "90660",
            "POP100": 13786,
            "GEOID": "5602590660",
            "CENTLAT": "+42.6077221",
            "AREAWATER": 19010714,
            "STATE": "56",
            "BASENAME": "Casper South",
            "OID": "27690241698254",
            "LSADC": "22",
            "FUNCSTAT": "S",
            "INTPTLAT": "+42.5862206",
            "NAME": "Casper South CCD",
            "OBJECTID": 2756,
            "CENTLON": "-106.3660910",
            "COUSUBCC": "Z5",
            "HU100": 6031,
            "AREALAND": 2036641482,
            "INTPTLON": "-106.3715723",
            "MTFCC": "G4040",
            "COUSUBNS": "01939695",
            "UR": "M",
            "COUNTY": "025"
          }
        ],
        "State Legislative Districts - Lower": [
          {
            "POP100": 10179,
            "GEOID": "56038",
            "CENTLAT": "+42.9414087",
            "SLDL": "038",
            "AREAWATER": 83514591,
            "STATE": "56",
            "BASENAME": "38",
            "OID": "213904690192350",
            "LSADC": "LL",
            "FUNCSTAT": "N",
            "INTPTLAT": "+42.9372081",
            "NAME": "State House District 38",
            "OBJECTID": 1126,
            "CENTLON": "-106.9044027",
            "LSY": "2018",
            "HU100": 4402,
            "AREALAND": 11466102284,
            "INTPTLON": "-106.9051494",
            "MTFCC": "G5220",
            "LDTYP": "O"
          }
        ],
        "Counties": [
          {
            "POP100": 79955,
            "GEOID": "56025",
            "CENTLAT": "+42.9614975",
            "AREAWATER": 90969261,
            "STATE": "56",
            "BASENAME": "Natrona",
            "OID": "27590241695414",
            "LSADC": "06",
            "FUNCSTAT": "A",
            "INTPTLAT": "+42.9776447",
            "NAME": "Natrona County",
            "OBJECTID": 2277,
            "CENTLON": "-106.7985179",
            "COUNTYCC": "H1",
            "COUNTYNS": "01605077",
            "AREALAND": 13831928341,
            "INTPTLON": "-106.7682192",
            "HU100": 36808,
            "MTFCC": "G4020",
            "UR": "M",
            "COUNTY": "025"
          }
        ],
        "116th Congressional Districts": [
          {
            "POP100": 576851,
            "GEOID": "5600",
            "CENTLAT": "+42.9960999",
            "CDSESSN": "116",
            "AREAWATER": 1867503715,
            "STATE": "56",
            "BASENAME": "Congressional District (at Large)",
            "OID": "211904692357415",
            "LSADC": "C1",
            "FUNCSTAT": "N",
            "INTPTLAT": "+42.9896591",
            "NAME": "Congressional District (at Large)",
            "OBJECTID": 134,
            "CENTLON": "-107.5514568",
            "HU100": 271887,
            "AREALAND": 251458712277,
            "INTPTLON": "-107.5443922",
            "CD116": "00",
            "MTFCC": "G5200"
          }
        ],
        "Census Tracts": [
          {
            "POP100": 2328,
            "GEOID": "56025001801",
            "CENTLAT": "+42.6015666",
            "AREAWATER": 18746098,
            "STATE": "56",
            "BASENAME": "18.01",
            "OID": "2079015489357631",
            "LSADC": "CT",
            "FUNCSTAT": "S",
            "INTPTLAT": "+42.5862206",
            "NAME": "Census Tract 18.01",
            "OBJECTID": 19057,
            "TRACT": "001801",
            "CENTLON": "-106.3668331",
            "HU100": 1399,
            "AREALAND": 1973876207,
            "INTPTLON": "-106.3715723",
            "MTFCC": "G5020",
            "UR": "M",
            "COUNTY": "025"
          }
        ],
        "Census Blocks": [
          {
            "SUFFIX": "",
            "POP100": 0,
            "GEOID": "560250018012215",
            "CENTLAT": "+42.5483410",
            "BLOCK": "2215",
            "AREAWATER": 0,
            "STATE": "56",
            "BASENAME": "2215",
            "OID": "210701003910837",
            "LSADC": "BK",
            "INTPTLAT": "+42.5483410",
            "FUNCSTAT": "S",
            "NAME": "Block 2215",
            "OBJECTID": 6829639,
            "TRACT": "001801",
            "CENTLON": "-106.7175858",
            "BLKGRP": "2",
            "AREALAND": 130757,
            "HU100": 0,
            "INTPTLON": "-106.7175858",
            "MTFCC": "G5040",
            "LWBLKTYP": "L",
            "UR": "R",
            "COUNTY": "025"
          }
        ]
      },
      "input": {
        "vintage": {
          "isDefault": true,
          "id": "2020",
          "vintageName": "Census2020_Census2020",
          "vintageDescription": "Census 2020 Vintage - Census 2020 Benchmark"
        },
        "location": {
          "x": -106.717536,
          "y": 42.548412
        },
        "benchmark": {
          "isDefault": false,
          "benchmarkDescription": "Public Address Ranges - Census 2020 Benchmark",
          "id": "2020",
          "benchmarkName": "Public_AR_Census2020"
        }
      }
    }
  }
}