{
  "created_at": "2025-05-01T15:40:52.003777+00:00",
  "elapsed": 0.140584,
  "encoding": "utf-8",
  "headers": {
    "Cache-Control": "private, no-store",
    "Connection": "keep-alive",
    "Content-Length": "3718",
    "Content-Type": "application/json",
    "Date": "Thu, 01 May 2025 15:40:51 GMT",
    "Strict-Transport-Security": "max-age=31536000",
    "Vary": "Origin",
    "X-Content-Type-Options": "nosniff",
    "X-Frame-Options": "DENY",
    "X-XSS-Protection": "1;mode=block"
  },
  "reason": "",
  "request": {
    "body": "",
    "cookies": {
      "TS0193e6a1": "01283c52a4ff367b3895f91b794499f991d32ef2569d74d392c0ed78c91e7f3d0ff67a45919cc964fba0e9db4e2e16461153e75477"
    },
    "headers": {
      "Accept": "*/*",
      "Accept-Encoding": "gzip, deflate, br",
      "Connection": "keep-alive",
      "Cookie": "TS0193e6a1=01283c52a4ff367b3895f91b794499f991d32ef2569d74d392c0ed78c91e7f3d0ff67a45919cc964fba0e9db4e2e16461153e75477",
      "User-Agent": "python-requests/2.32.3"
    },
    "method": "GET",
    "url": "https://geocoding.geo.census.gov/geocoder/geographies/coordinates?benchmark=Public_AR_Census2020&format=json&vintage=Census2020_Census2020&x=-86.20813&y=30.87576"
  },
  "status_code": 200,
  "url": "https://geocoding.geo.census.gov/geocoder/geographies/coordinates?benchmark=Public_AR_Census2020&format=json&vintage=Census2020_Census2020&x=-86.20813&y=30.87576",
  "_decoded_content": {
    "result": {
      "geographies": {
        "State Legislative Districts - Upper": [
          {
            "POP100": 526550,
            "GEOID": "12002",
            "CENTLAT": "+30.5371543",
            "AREAWATER": 3806386892,
            "STATE": "12",
            "BASENAME": "2",
            "OID": "212904690226271",
            "LSADC": "LU",
            "SLDU": "002",
            "FUNCSTAT": "N",
            "INTPTLAT": "+30.5452770",
            "NAME": "State Senate District 2",
            "OBJECTID": 1393,
            "CENTLON": "-085.8664042",
            "LSY": "2018",
            "HU100": 287953,
            "AREALAND": 11483666767,
            "INTPTLON": "-085.8742266",
            "MTFCC": "G5210",
            "LDTYP": "O"
          }
        ],
        "States": [
          {
            "STATENS": "00294478",
            "POP100": 21538187,
            "GEOID": "12",
            "CENTLAT": "+28.4062029",
            "AREAWATER": 45975808217,
            "STATE": "12",
            "BASENAME": "Florida",
            "STUSAB": "FL",
            "OID": "2749046365780",
            "LSADC": "00",
            "FUNCSTAT": "A",
            "INTPTLAT": "+28.3989775",
            "DIVISION": "5",
            "NAME": "Florida",
            "REGION": "3",
            "OBJECTID": 17,
            "CENTLON": "-082.5022125",
            "AREALAND": 138958484319,
            "INTPTLON": "-082.5143005",
            "HU100": 9865350,
            "MTFCC": "G4000",
            "UR": "M"
          }
        ],
        "County Subdivisions": [
          {
            "COUSUB": "92665",
            "POP100": 9824,
            "GEOID": "1213192665",
            "CENTLAT": "+30.8782610",
            "AREAWATER": 28108190,
            "STATE": "12",
            "BASENAME": "Paxton-Darlington",
            "OID": "2769091152605",
            "LSADC": "22",
            "FUNCSTAT": "S",
            "INTPTLAT": "+30.8732729",
            "NAME": "Paxton-Darlington CCD",
            "OBJECTID": 29556,
            "CENTLON": "-086.2244780",
            "COUSUBCC": "Z5",
            "HU100": 4581,
            "AREALAND": 825355571,
            "INTPTLON": "-086.2247988",
            "MTFCC": "G4040",
            "COUSUBNS": "01935892",
            "UR": "R",
            "COUNTY": "131"
          }
        ],
        "State Legislative Districts - Lower": [
          {
            "POP100": 178785,
            "GEOID": "12005",
            "CENTLAT": "+30.6596464",
            "SLDL": "005",
            "AREAWATER": 1178570053,
            "STATE": "12",
            "BASENAME": "5",
            "OID": "213904690227408",
            "LSADC": "LL",
            "FUNCSTAT": "N",
            "INTPTLAT": "+30.6561224",
            "NAME": "State House District 5",
            "OBJECTID": 112,
            "CENTLON": "-085.7588322",
            "LSY": "2018",
            "HU100": 100112,
            "AREALAND": 8592941993,
            "INTPTLON": "-085.7534567",
            "MTFCC": "G5220",
            "LDTYP": "O"
          }
        ],
        "Counties": [
          {
            "POP100": 75305,
            "GEOID": "12131",
            "CENTLAT": "+30.5707767",
            "AREAWATER": 961289588,
            "STATE": "12",
            "BASENAME": "Walton",
            "OID": "2759091152601",
            "LSADC": "06",
            "FUNCSTAT": "A",
            "INTPTLAT": "+30.5712465",
            "NAME": "Walton County",
            "OBJECTID": 65,
            "CENTLON": "-086.1743779",
            "COUNTYCC": "H1",
            "COUNTYNS": "00295727",
            "AREALAND": 2689165614,
            "INTPTLON": "-086.1627980",
            "HU100": 56197,
            "MTFCC": "G4020",
            "UR": "M",
            "COUNTY": "131"
          }
        ],
        "116th Congressional Districts": [
          {
            "POP100": 807881,
            "GEOID": "1201",
            "CENTLAT": "+30.6184008",
            "CDSESSN": "116",
            "AREAWATER": 3559638678,
            "STATE": "12",
            "BASENAME": "1",
            "OID": "211904690220908",
            "LSADC": "C2",
            "FUNCSTAT": "N",
            "INTPTLAT": "+30.6135464",
            "NAME": "Congressional District 1",
            "OBJECTID": 286,
            "CENTLON": "-086.6761984",
            "HU100": 384093,
            "AREALAND": 10407256217,
            "INTPTLON": "-086.6728965",
            "CD116": "01",
            "MTFCC": "G5200"
          }
        ],
        "Census Tracts": [
          {
            "POP100": 3105,
            "GEOID": "12131950102",
            "CENTLAT": "+30.9001685",
            "AREAWATER": 23582903,
            "STATE": "12",
            "BASENAME": "9501.02",
            "OID": "207903717578486",
            "LSADC": "CT",
            "FUNCSTAT": "S",
            "INTPTLAT": "+30.8883500",
            "NAME": "Census Tract 9501.02",
            "OBJECTID": 72753,
            "TRACT": "950102",
            "CENTLON": "-086.1504907",
            "HU100": 1521,
            "AREALAND": 449911677,
            "INTPTLON": "-086.1365995",
            "MTFCC": "G5020",
            "UR": "R",
            "COUNTY": "131"
          }
        ],
        "Census Blocks": [
          {
            "SUFFIX": "",
            "POP100": 12,
            "GEOID": "121319501024022",
            "CENTLAT": "+30.8831248",
            "BLOCK": "4022",
            "AREAWATER": 13793,
            "STATE": "12",
            "BASENAME": "4022",
            "OID": "210701001194945",
            "LSADC": "BK",
            "INTPTLAT": "+30.8831126",
            "FUNCSTAT": "S",
            "NAME": "Block 4022",
            "OBJECTID": 736465,
            "TRACT": "950102",
            "CENTLON": "-086.2088905",
            "BLKGRP": "4",
            "AREALAND": 1664555,
            "HU100": 7,
            "INTPTLON": "-086.2088885",
            "MTFCC": "G5040",
            "LWBLKTYP": "B",
            "UR": "R",
            "COUNTY": "131"
          }
        ]
      },
      "input": {
        "vintage": {
          "isDefault": true,
          "id": "2020",
          "vintageName": "Census2020_Census2020",
          "vintageDescription": "Census 2020 Vintage - Census 2020 Benchmark"
        },
        "location": {
          "x": -86.20813,
          "y": 30.87576
        },
        "benchmark": {
          "isDefault": false,
          "benchmarkDescription": "Public Address Ranges - Census 2020 Benchmark",
          "id": "2020",
          "benchmarkName": "Public_AR_Census2020"
        }
      }
    }
  }
}