{
  "created_at": "2025-05-01T15:37:51.609442+00:00",
  "elapsed": 0.447936,
  "encoding": "utf-8",
  "headers": {
    "Cache-Control": "private, no-store",
    "Connection": "keep-alive",
    "Content-Length": "5008",
    "Content-Type": "application/json",
    "Date": "Thu, 01 May 2025 15:37:51 GMT",
    "Strict-Transport-Security": "max-age=31536000",
    "Vary": "Origin",
    "X-Content-Type-Options": "nosniff",
    "X-Frame-Options": "DENY",
    "X-XSS-Protection": "1;mode=block"
  },
  "reason": "",
  "request": {
    "body": "",
    "cookies": {
      "TS0193e6a1": "01283c52a4685389b04d24928d59124b3a512fb85755dc771bca47a6b2a92df4d0a97e08410c6afeacdef43c9a1b82f5a09618a199"
    },
    "headers": {
      "Accept": "*/*",
      "Accept-Encoding": "gzip, deflate, br",
      "Connection": "keep-alive",
      "Cookie": "TS0193e6a1=01283c52a4685389b04d24928d59124b3a512fb85755dc771bca47a6b2a92df4d0a97e08410c6afeacdef43c9a1b82f5a09618a199",
      "User-Agent": "python-requests/2.32.3"
    },
    "method": "GET",
    "url": "https://geocoding.geo.census.gov/geocoder/geographies/coordinates?benchmark=Public_AR_Census2020&format=json&vintage=Census2020_Census2020&x=-76.82843&y=38.73169"
  },
  "status_code": 200,
  "url": "https://geocoding.geo.census.gov/geocoder/geographies/coordinates?benchmark=Public_AR_Census2020&format=json&vintage=Census2020_Census2020&x=-76.82843&y=38.73169",
  "_decoded_content": {
    "result": {
      "geographies": {
        "State Legislative Districts - Upper": [
          {
            "POP100": 141454,
            "GEOID": "24027",
            "CENTLAT": "+38.6191668",
            "AREAWATER": 9214611,
            "STATE": "24",
            "BASENAME": "27",
            "OID": "212904691844434",
            "LSADC": "LU",
            "SLDU": "027",
            "FUNCSTAT": "N",
            "INTPTLAT": "+38.6210019",
            "NAME": "State Senate District 27",
            "OBJECTID": 1071,
            "CENTLON": "-076.6935199",
            "LSY": "2018",
            "HU100": 51725,
            "AREALAND": 935746784,
            "INTPTLON": "-076.7048380",
            "MTFCC": "G5210",
            "LDTYP": "O"
          }
        ],
        "States": [
          {
            "STATENS": "01714934",
            "POP100": 6177224,
            "GEOID": "24",
            "CENTLAT": "+38.9463607",
            "AREAWATER": 6979171386,
            "STATE": "24",
            "BASENAME": "Maryland",
            "STUSAB": "MD",
            "OID": "27490140608205",
            "LSADC": "00",
            "FUNCSTAT": "A",
            "INTPTLAT": "+38.9466584",
            "DIVISION": "5",
            "NAME": "Maryland",
            "REGION": "3",
            "OBJECTID": 20,
            "CENTLON": "-076.6789663",
            "AREALAND": 25151895765,
            "INTPTLON": "-076.6744939",
            "HU100": 2530844,
            "MTFCC": "G4000",
            "UR": "M"
          }
        ],
        "Combined Statistical Areas": [
          {
            "POP100": 9973383,
            "GEOID": "548",
            "CENTLAT": "+39.0282791",
            "AREAWATER": 4067866689,
            "BASENAME": "Washington-Baltimore-Arlington, DC-MD-VA-WV-PA",
            "OID": "2619013782255247",
            "LSADC": "M0",
            "FUNCSTAT": "S",
            "INTPTLAT": "+39.0246056",
            "NAME": "Washington-Baltimore-Arlington, DC-MD-VA-WV-PA CSA",
            "CSA": "548",
            "OBJECTID": 103,
            "CENTLON": "-077.3083318",
            "HU100": 4006033,
            "AREALAND": 32735838394,
            "INTPTLON": "-077.3105306",
            "MTFCC": "G3100"
          }
        ],
        "2020 Urban Areas - Corrected": [
          {
            "GEOID": "92242",
            "CENTLAT": "+38.8953362",
            "AREAWATER": 67538846,
            "BASENAME": "Washington--Arlington, DC--VA--MD",
            "OID": "27021158105937",
            "UA": "92242",
            "LSADC": "67",
            "FUNCSTAT": "S",
            "INTPTLAT": "+38.8959429",
            "NAME": "Washington--Arlington, DC--VA--MD Urban Area",
            "OBJECTID": 612,
            "CENTLON": "-077.1822188",
            "AREALAND": 3352762591,
            "INTPTLON": "-077.1830768",
            "MTFCC": "G3500"
          }
        ],
        "County Subdivisions": [
          {
            "COUSUB": "90980",
            "POP100": 20480,
            "GEOID": "2403390980",
            "CENTLAT": "+38.7006243",
            "AREAWATER": 761316,
            "STATE": "24",
            "BASENAME": "11, Brandywine",
            "OID": "27690286313752",
            "LSADC": "28",
            "FUNCSTAT": "N",
            "INTPTLAT": "+38.7038463",
            "NAME": "District 11, Brandywine",
            "OBJECTID": 23783,
            "CENTLON": "-076.8436236",
            "COUSUBCC": "Z1",
            "HU100": 7064,
            "AREALAND": 122888690,
            "INTPTLON": "-076.8397759",
            "MTFCC": "G4040",
            "COUSUBNS": "01929448",
            "UR": "M",
            "COUNTY": "033"
          }
        ],
        "Census Designated Places": [
          {
            "NECTAPCI": "N",
            "POP100": 2720,
            "GEOID": "2420925",
            "CENTLAT": "+38.7457876",
            "AREAWATER": 3141233,
            "STATE": "24",
            "BASENAME": "Croom",
            "OID": "280903716512994",
            "LSADC": "57",
            "PLACE": "20925",
            "FUNCSTAT": "S",
            "INTPTLAT": "+38.7397992",
            "NAME": "Croom CDP",
            "OBJECTID": 25517,
            "PLACECC": "U1",
            "CENTLON": "-076.7554690",
            "CBSAPCI": "N",
            "HU100": 1063,
            "AREALAND": 88559891,
            "INTPTLON": "-076.7551918",
            "PLACENS": "02583603",
            "MTFCC": "G4210",
            "UR": "M"
          }
        ],
        "State Legislative Districts - Lower": [
          {
            "POP100": 45496,
            "GEOID": "2427B",
            "CENTLAT": "+38.6867146",
            "SLDL": "27B",
            "AREAWATER": 5360434,
            "STATE": "24",
            "BASENAME": "27B",
            "OID": "213904691844733",
            "LSADC": "L6",
            "FUNCSTAT": "N",
            "INTPTLAT": "+38.6610964",
            "NAME": "State Legislative Subdistrict 27B",
            "OBJECTID": 1500,
            "CENTLON": "-076.6966413",
            "LSY": "2018",
            "HU100": 15706,
            "AREALAND": 337059976,
            "INTPTLON": "-076.6983891",
            "MTFCC": "G5220",
            "LDTYP": "O"
          }
        ],
        "Counties": [
          {
            "POP100": 967201,
            "GEOID": "24033",
            "CENTLAT": "+38.8293079",
            "AREAWATER": 41922695,
            "STATE": "24",
            "BASENAME": "Prince George's",
            "OID": "27590286309965",
            "LSADC": "06",
            "FUNCSTAT": "A",
            "INTPTLAT": "+38.8292778",
            "NAME": "Prince George's County",
            "OBJECTID": 1339,
            "CENTLON": "-076.8472801",
            "COUNTYCC": "H1",
            "COUNTYNS": "01714670",
            "AREALAND": 1250057213,
            "INTPTLON": "-076.8481880",
            "HU100": 359957,
            "MTFCC": "G4020",
            "UR": "M",
            "COUNTY": "033"
          }
        ],
        "116th Congressional Districts": [
          {
            "POP100": 795379,
            "GEOID": "2405",
            "CENTLAT": "+38.4746485",
            "CDSESSN": "116",
            "AREAWATER": 2066519525,
            "STATE": "24",
            "BASENAME": "5",
            "OID": "211904690760337",
            "LSADC": "C2",
            "FUNCSTAT": "N",
            "INTPTLAT": "+38.4718173",
            "NAME": "Congressional District 5",
            "OBJECTID": 199,
            "CENTLON": "-076.7132342",
            "HU100": 295964,
            "AREALAND": 3840026634,
            "INTPTLON": "-076.7120357",
            "CD116": "05",
            "MTFCC": "G5200"
          }
        ],
        "Census Tracts": [
          {
            "POP100": 5725,
            "GEOID": "24033801004",
            "CENTLAT": "+38.7206411",
            "AREAWATER": 219049,
            "STATE": "24",
            "BASENAME": "8010.04",
            "OID": "207903711045604",
            "LSADC": "CT",
            "FUNCSTAT": "S",
            "INTPTLAT": "+38.7250838",
            "NAME": "Census Tract 8010.04",
            "OBJECTID": 42574,
            "TRACT": "801004",
            "CENTLON": "-076.8552584",
            "HU100": 1902,
            "AREALAND": 36523559,
            "INTPTLON": "-076.8513765",
            "MTFCC": "G5020",
            "UR": "M",
            "COUNTY": "033"
          }
        ],
        "Census Blocks": [
          {
            "SUFFIX": "",
            "POP100": 22,
            "GEOID": "240338010041010",
            "CENTLAT": "+38.7327175",
            "BLOCK": "1010",
            "AREAWATER": 0,
            "STATE": "24",
            "BASENAME": "1010",
            "OID": "210701008480181",
            "LSADC": "BK",
            "INTPTLAT": "+38.7327175",
            "FUNCSTAT": "S",
            "NAME": "Block 1010",
            "OBJECTID": 346457,
            "TRACT": "801004",
            "CENTLON": "-076.8266879",
            "BLKGRP": "1",
            "AREALAND": 116531,
            "HU100": 5,
            "INTPTLON": "-076.8266879",
            "MTFCC": "G5040",
            "LWBLKTYP": "L",
            "UR": "U",
            "COUNTY": "033"
          }
        ]
      },
      "input": {
        "vintage": {
          "isDefault": true,
          "id": "2020",
          "vintageName": "Census2020_Census2020",
          "vintageDescription": "Census 2020 Vintage - Census 2020 Benchmark"
        },
        "location": {
          "x": -76.82843,
          "y": 38.73169
        },
        "benchmark": {
          "isDefault": false,
          "benchmarkDescription": "Public Address Ranges - Census 2020 Benchmark",
          "id": "2020",
          "benchmarkName": "Public_AR_Census2020"
        }
      }
    }
  }
}