{
  "created_at": "2025-05-01T15:41:26.043128+00:00",
  "elapsed": 0.203933,
  "encoding": "utf-8",
  "headers": {
    "Cache-Control": "private, no-store",
    "Connection": "keep-alive",
    "Content-Length": "4966",
    "Content-Type": "application/json",
    "Date": "Thu, 01 May 2025 15:41:26 GMT",
    "Strict-Transport-Security": "max-age=31536000",
    "Vary": "Origin",
    "X-Content-Type-Options": "nosniff",
    "X-Frame-Options": "DENY",
    "X-XSS-Protection": "1;mode=block"
  },
  "reason": "",
  "request": {
    "body": "",
    "cookies": {
      "TS0193e6a1": "01283c52a4ff367b3895f91b794499f991d32ef2569d74d392c0ed78c91e7f3d0ff67a45919cc964fba0e9db4e2e16461153e75477"
    },
    "headers": {
      "Accept": "*/*",
      "Accept-Encoding": "gzip, deflate, br",
      "Connection": "keep-alive",
      "Cookie": "TS0193e6a1=01283c52a4ff367b3895f91b794499f991d32ef2569d74d392c0ed78c91e7f3d0ff67a45919cc964fba0e9db4e2e16461153e75477",
      "User-Agent": "python-requests/2.32.3"
    },
    "method": "GET",
    "url": "https://geocoding.geo.census.gov/geocoder/geographies/coordinates?benchmark=Public_AR_Census2020&format=json&vintage=Census2020_Census2020&x=-71.1061&y=41.8653"
  },
  "status_code": 200,
  "url": "https://geocoding.geo.census.gov/geocoder/geographies/coordinates?benchmark=Public_AR_Census2020&format=json&vintage=Census2020_Census2020&x=-71.1061&y=41.8653",
  "_decoded_content": {
    "result": {
      "geographies": {
        "State Legislative Districts - Upper": [
          {
            "POP100": 182588,
            "GEOID": "25036",
            "CENTLAT": "+41.8568823",
            "AREAWATER": 84635942,
            "STATE": "25",
            "BASENAME": "First Plymouth & Bristol",
            "OID": "212904693077271",
            "LSADC": "07",
            "SLDU": "036",
            "FUNCSTAT": "N",
            "INTPTLAT": "+41.8615743",
            "NAME": "First Plymouth & Bristol District",
            "OBJECTID": 1529,
            "CENTLON": "-070.9072361",
            "LSY": "2018",
            "HU100": 75562,
            "AREALAND": 749207206,
            "INTPTLON": "-070.9108494",
            "MTFCC": "G5210",
            "LDTYP": "O"
          }
        ],
        "States": [
          {
            "STATENS": "00606926",
            "POP100": 7029917,
            "GEOID": "25",
            "CENTLAT": "+42.1618490",
            "AREAWATER": 7130653806,
            "STATE": "25",
            "BASENAME": "Massachusetts",
            "STUSAB": "MA",
            "OID": "27490203627104",
            "LSADC": "00",
            "FUNCSTAT": "A",
            "INTPTLAT": "+42.1565196",
            "DIVISION": "1",
            "NAME": "Massachusetts",
            "REGION": "1",
            "OBJECTID": 10,
            "CENTLON": "-071.4975238",
            "AREALAND": 20204396898,
            "INTPTLON": "-071.4895915",
            "HU100": 2998537,
            "MTFCC": "G4000",
            "UR": "M"
          }
        ],
        "Combined Statistical Areas": [
          {
            "POP100": 8466186,
            "GEOID": "148",
            "CENTLAT": "+42.3593610",
            "AREAWATER": 7170162236,
            "BASENAME": "Boston-Worcester-Providence, MA-RI-NH-CT",
            "OID": "2619013782255090",
            "LSADC": "M0",
            "FUNCSTAT": "S",
            "INTPTLAT": "+42.3619187",
            "NAME": "Boston-Worcester-Providence, MA-RI-NH-CT CSA",
            "CSA": "148",
            "OBJECTID": 83,
            "CENTLON": "-071.2719973",
            "HU100": 3604952,
            "AREALAND": 25128574279,
            "INTPTLON": "-071.2724983",
            "MTFCC": "G3100"
          }
        ],
        "2020 Urban Areas - Corrected": [
          {
            "GEOID": "09271",
            "CENTLAT": "+42.3794881",
            "AREAWATER": 185677268,
            "BASENAME": "Boston, MA--NH",
            "OID": "27021206517502",
            "UA": "09271",
            "LSADC": "67",
            "FUNCSTAT": "S",
            "INTPTLAT": "+42.3789986",
            "NAME": "Boston, MA--NH Urban Area",
            "OBJECTID": 407,
            "CENTLON": "-071.1422204",
            "AREALAND": 4288728505,
            "INTPTLON": "-071.1423438",
            "MTFCC": "G3500"
          }
        ],
        "County Subdivisions": [
          {
            "COUSUB": "69170",
            "POP100": 59408,
            "GEOID": "2500569170",
            "CENTLAT": "+41.9035780",
            "AREAWATER": 4418829,
            "STATE": "25",
            "BASENAME": "Taunton",
            "OID": "27690406240864",
            "LSADC": "25",
            "FUNCSTAT": "F",
            "INTPTLAT": "+41.9033244",
            "NAME": "Taunton city",
            "OBJECTID": 11288,
            "CENTLON": "-071.0942613",
            "COUSUBCC": "C5",
            "HU100": 24965,
            "AREALAND": 120973247,
            "INTPTLON": "-071.0949874",
            "MTFCC": "G4040",
            "COUSUBNS": "00619440",
            "UR": "M",
            "COUNTY": "005"
          }
        ],
        "State Legislative Districts - Lower": [
          {
            "POP100": 44702,
            "GEOID": "25073",
            "CENTLAT": "+41.7961661",
            "SLDL": "073",
            "AREAWATER": 18149020,
            "STATE": "25",
            "BASENAME": "5th Bristol",
            "OID": "213904693077451",
            "LSADC": "07",
            "FUNCSTAT": "N",
            "INTPTLAT": "+41.7965245",
            "NAME": "5th Bristol District",
            "OBJECTID": 4609,
            "CENTLON": "-071.1604400",
            "LSY": "2018",
            "HU100": 18048,
            "AREALAND": 116821009,
            "INTPTLON": "-071.1596688",
            "MTFCC": "G5220",
            "LDTYP": "O"
          }
        ],
        "Incorporated Places": [
          {
            "NECTAPCI": "N",
            "POP100": 59408,
            "GEOID": "2569170",
            "CENTLAT": "+41.9035780",
            "AREAWATER": 4418829,
            "STATE": "25",
            "BASENAME": "Taunton",
            "OID": "27890406245360",
            "LSADC": "25",
            "PLACE": "69170",
            "FUNCSTAT": "A",
            "INTPTLAT": "+41.9033244",
            "NAME": "Taunton city",
            "OBJECTID": 6609,
            "PLACECC": "C5",
            "CENTLON": "-071.0942613",
            "CBSAPCI": "N",
            "HU100": 24965,
            "AREALAND": 120973247,
            "INTPTLON": "-071.0949874",
            "PLACENS": "00619440",
            "MTFCC": "G4110",
            "UR": "M"
          }
        ],
        "Counties": [
          {
            "POP100": 579200,
            "GEOID": "25005",
            "CENTLAT": "+41.7567464",
            "AREAWATER": 357461179,
            "STATE": "25",
            "BASENAME": "Bristol",
            "OID": "27590264619750",
            "LSADC": "06",
            "FUNCSTAT": "A",
            "INTPTLAT": "+41.7485884",
            "NAME": "Bristol County",
            "OBJECTID": 1083,
            "CENTLON": "-071.0880848",
            "COUNTYCC": "H1",
            "COUNTYNS": "00606929",
            "AREALAND": 1432553462,
            "INTPTLON": "-071.0888940",
            "HU100": 243464,
            "MTFCC": "G4020",
            "UR": "M",
            "COUNTY": "005"
          }
        ],
        "116th Congressional Districts": [
          {
            "POP100": 777137,
            "GEOID": "2504",
            "CENTLAT": "+41.9909334",
            "CDSESSN": "116",
            "AREAWATER": 86336453,
            "STATE": "25",
            "BASENAME": "4",
            "OID": "211904690191888",
            "LSADC": "C2",
            "FUNCSTAT": "N",
            "INTPTLAT": "+41.9972149",
            "NAME": "Congressional District 4",
            "OBJECTID": 345,
            "CENTLON": "-071.2318909",
            "HU100": 304979,
            "AREALAND": 1730853132,
            "INTPTLON": "-071.2275358",
            "CD116": "04",
            "MTFCC": "G5200"
          }
        ],
        "Census Tracts": [
          {
            "POP100": 5763,
            "GEOID": "25005613902",
            "CENTLAT": "+41.8750643",
            "AREAWATER": 245850,
            "STATE": "25",
            "BASENAME": "6139.02",
            "OID": "207903711031030",
            "LSADC": "CT",
            "FUNCSTAT": "S",
            "INTPTLAT": "+41.8727942",
            "NAME": "Census Tract 6139.02",
            "OBJECTID": 80267,
            "TRACT": "613902",
            "CENTLON": "-071.1120598",
            "HU100": 2338,
            "AREALAND": 8045314,
            "INTPTLON": "-071.1136635",
            "MTFCC": "G5020",
            "UR": "U",
            "COUNTY": "005"
          }
        ],
        "Census Blocks": [
          {
            "SUFFIX": "",
            "POP100": 336,
            "GEOID": "250056139023006",
            "CENTLAT": "+41.8629304",
            "BLOCK": "3006",
            "AREAWATER": 0,
            "STATE": "25",
            "BASENAME": "3006",
            "OID": "210701007764276",
            "LSADC": "BK",
            "INTPTLAT": "+41.8629304",
            "FUNCSTAT": "S",
            "NAME": "Block 3006",
            "OBJECTID": 7565934,
            "TRACT": "613902",
            "CENTLON": "-071.1098325",
            "BLKGRP": "3",
            "AREALAND": 1073904,
            "HU100": 131,
            "INTPTLON": "-071.1098325",
            "MTFCC": "G5040",
            "LWBLKTYP": "L",
            "UR": "U",
            "COUNTY": "005"
          }
        ]
      },
      "input": {
        "vintage": {
          "isDefault": true,
          "id": "2020",
          "vintageName": "Census2020_Census2020",
          "vintageDescription": "Census 2020 Vintage - Census 2020 Benchmark"
        },
        "location": {
          "x": -71.1061,
          "y": 41.8653
        },
        "benchmark": {
          "isDefault": false,
          "benchmarkDescription": "Public Address Ranges - Census 2020 Benchmark",
          "id": "2020",
          "benchmarkName": "Public_AR_Census2020"
        }
      }
    }
  }
}