{
  "created_at": "2025-05-01T15:43:46.365019+00:00",
  "elapsed": 0.143405,
  "encoding": "utf-8",
  "headers": {
    "Cache-Control": "private, no-store",
    "Connection": "keep-alive",
    "Content-Length": "3693",
    "Content-Type": "application/json",
    "Date": "Thu, 01 May 2025 15:43:46 GMT",
    "Strict-Transport-Security": "max-age=31536000",
    "Vary": "Origin",
    "X-Content-Type-Options": "nosniff",
    "X-Frame-Options": "DENY",
    "X-XSS-Protection": "1;mode=block"
  },
  "reason": "",
  "request": {
    "body": "",
    "cookies": {
      "TS0193e6a1": "01283c52a432a7c25dd9abac56daedd10b404d4f500ebb4c5c3ecdfde3039778bfec59e5c6509ca00cfc39642994bb0c556f4c4c18"
    },
    "headers": {
      "Accept": "*/*",
      "Accept-Encoding": "gzip, deflate, br",
      "Connection": "keep-alive",
      "Cookie": "TS0193e6a1=01283c52a432a7c25dd9abac56daedd10b404d4f500ebb4c5c3ecdfde3039778bfec59e5c6509ca00cfc39642994bb0c556f4c4c18",
      "User-Agent": "python-requests/2.32.3"
    },
    "method": "GET",
    "url": "https://geocoding.geo.census.gov/geocoder/geographies/coordinates?benchmark=Public_AR_Census2020&format=json&vintage=Census2020_Census2020&x=-107.75056&y=32.165833"
  },
  "status_code": 200,
  "url": "https://geocoding.geo.census.gov/geocoder/geographies/coordinates?benchmark=Public_AR_Census2020&format=json&vintage=Census2020_Census2020&x=-107.75056&y=32.165833",
  "_decoded_content": {
    "result": {
      "geographies": {
        "State Legislative Districts - Upper": [
          {
            "POP100": 48590,
            "GEOID": "35035",
            "CENTLAT": "+32.4680780",
            "AREAWATER": 172486474,
            "STATE": "35",
            "BASENAME": "35",
            "OID": "212904692171342",
            "LSADC": "LU",
            "SLDU": "035",
            "FUNCSTAT": "N",
            "INTPTLAT": "+32.3697833",
            "NAME": "State Senate District 35",
            "OBJECTID": 1447,
            "CENTLON": "-107.8025278",
            "LSY": "2018",
            "HU100": 25033,
            "AREALAND": 29045533258,
            "INTPTLON": "-107.8129778",
            "MTFCC": "G5210",
            "LDTYP": "O"
          }
        ],
        "States": [
          {
            "STATENS": "00897535",
            "POP100": 2117522,
            "GEOID": "35",
            "CENTLAT": "+34.4075785",
            "AREAWATER": 726482115,
            "STATE": "35",
            "BASENAME": "New Mexico",
            "STUSAB": "NM",
            "OID": "27490100936841",
            "LSADC": "00",
            "FUNCSTAT": "A",
            "INTPTLAT": "+34.4346843",
            "DIVISION": "8",
            "NAME": "New Mexico",
            "REGION": "4",
            "OBJECTID": 28,
            "CENTLON": "-106.1126593",
            "AREALAND": 314198560935,
            "INTPTLON": "-106.1316181",
            "HU100": 940859,
            "MTFCC": "G4000",
            "UR": "M"
          }
        ],
        "County Subdivisions": [
          {
            "COUSUB": "90930",
            "POP100": 21161,
            "GEOID": "3502990930",
            "CENTLAT": "+32.0191916",
            "AREAWATER": 399743,
            "STATE": "35",
            "BASENAME": "Deming South",
            "OID": "27690295877187",
            "LSADC": "22",
            "FUNCSTAT": "S",
            "INTPTLAT": "+32.0044082",
            "NAME": "Deming South CCD",
            "OBJECTID": 18088,
            "CENTLON": "-107.7533468",
            "COUSUBCC": "Z5",
            "HU100": 9980,
            "AREALAND": 4531991851,
            "INTPTLON": "-107.7202392",
            "MTFCC": "G4040",
            "COUSUBNS": "01937520",
            "UR": "M",
            "COUNTY": "029"
          }
        ],
        "State Legislative Districts - Lower": [
          {
            "POP100": 29332,
            "GEOID": "35032",
            "CENTLAT": "+32.0234502",
            "SLDL": "032",
            "AREAWATER": 24193415,
            "STATE": "35",
            "BASENAME": "32",
            "OID": "213904692176388",
            "LSADC": "LL",
            "FUNCSTAT": "N",
            "INTPTLAT": "+32.0325279",
            "NAME": "State House District 32",
            "OBJECTID": 3634,
            "CENTLON": "-108.2610178",
            "LSY": "2018",
            "HU100": 13584,
            "AREALAND": 17300110299,
            "INTPTLON": "-108.2461850",
            "MTFCC": "G5220",
            "LDTYP": "O"
          }
        ],
        "Counties": [
          {
            "POP100": 25427,
            "GEOID": "35029",
            "CENTLAT": "+32.1819257",
            "AREAWATER": 433660,
            "STATE": "35",
            "BASENAME": "Luna",
            "OID": "27590295817664",
            "LSADC": "06",
            "FUNCSTAT": "A",
            "INTPTLAT": "+32.1845231",
            "NAME": "Luna County",
            "OBJECTID": 2892,
            "CENTLON": "-107.7498512",
            "COUNTYCC": "H1",
            "COUNTYNS": "00933057",
            "AREALAND": 7679776933,
            "INTPTLON": "-107.7471911",
            "HU100": 11508,
            "MTFCC": "G4020",
            "UR": "M",
            "COUNTY": "029"
          }
        ],
        "116th Congressional Districts": [
          {
            "POP100": 714022,
            "GEOID": "3502",
            "CENTLAT": "+33.3830875",
            "CDSESSN": "116",
            "AREAWATER": 408390188,
            "STATE": "35",
            "BASENAME": "2",
            "OID": "211904690703526",
            "LSADC": "C2",
            "FUNCSTAT": "N",
            "INTPTLAT": "+33.3852613",
            "NAME": "Congressional District 2",
            "OBJECTID": 433,
            "CENTLON": "-106.2970098",
            "HU100": 314495,
            "AREALAND": 185821828656,
            "INTPTLON": "-106.2994424",
            "CD116": "02",
            "MTFCC": "G5200"
          }
        ],
        "Census Tracts": [
          {
            "POP100": 3589,
            "GEOID": "35029000401",
            "CENTLAT": "+31.9539070",
            "AREAWATER": 0,
            "STATE": "35",
            "BASENAME": "4.01",
            "OID": "2079015503478161",
            "LSADC": "CT",
            "FUNCSTAT": "S",
            "INTPTLAT": "+31.9539070",
            "NAME": "Census Tract 4.01",
            "OBJECTID": 32461,
            "TRACT": "000401",
            "CENTLON": "-107.7715160",
            "HU100": 1660,
            "AREALAND": 819152951,
            "INTPTLON": "-107.7715160",
            "MTFCC": "G5020",
            "UR": "R",
            "COUNTY": "029"
          }
        ],
        "Census Blocks": [
          {
            "SUFFIX": "",
            "POP100": 20,
            "GEOID": "350290004012041",
            "CENTLAT": "+32.1651805",
            "BLOCK": "2041",
            "AREAWATER": 0,
            "STATE": "35",
            "BASENAME": "2041",
            "OID": "210701002902059",
            "LSADC": "BK",
            "INTPTLAT": "+32.1651805",
            "FUNCSTAT": "S",
            "NAME": "Block 2041",
            "OBJECTID": 5987482,
            "TRACT": "000401",
            "CENTLON": "-107.7467095",
            "BLKGRP": "2",
            "AREALAND": 331641,
            "HU100": 2,
            "INTPTLON": "-107.7467095",
            "MTFCC": "G5040",
            "LWBLKTYP": "L",
            "UR": "R",
            "COUNTY": "029"
          }
        ]
      },
      "input": {
        "vintage": {
          "isDefault": true,
          "id": "2020",
          "vintageName": "Census2020_Census2020",
          "vintageDescription": "Census 2020 Vintage - Census 2020 Benchmark"
        },
        "location": {
          "x": -107.75056,
          "y": 32.165833
        },
        "benchmark": {
          "isDefault": false,
          "benchmarkDescription": "Public Address Ranges - Census 2020 Benchmark",
          "id": "2020",
          "benchmarkName": "Public_AR_Census2020"
        }
      }
    }
  }
}